main/__init__.py
main/main.py
podloot/__init__.py
podloot/main.py
podloot/podcast_downloader.py
src/__init__.py
src/main/__init__.py
src/main/main.py
src/podloot/__init__.py
src/podloot/podcast_downloader.py
podloot-0.1.dist-info/LICENSE
podloot-0.1.dist-info/METADATA
podloot-0.1.dist-info/WHEEL
podloot-0.1.dist-info/entry_points.txt
podloot-0.1.dist-info/top_level.txt
podloot-0.1.dist-info/RECORD
