Metadata-Version: 2.1
Name: podloot
Version: 0.1
Summary: A podcast downloader and manager using RSS feeds
Home-page: https://github.com/gusanmaz/podloot
Author: Guvenc Usanmaz
Author-email: gusanmaz@gmail.com
Classifier: Development Status :: 3 - Alpha
Classifier: License :: OSI Approved :: MIT License
Classifier: Programming Language :: Python :: 3
Classifier: Programming Language :: Python :: 3.6
Classifier: Programming Language :: Python :: 3.7
Classifier: Programming Language :: Python :: 3.8
Classifier: Programming Language :: Python :: 3.9
License-File: LICENSE
Requires-Dist: brotli (==1.0.9)
Requires-Dist: brotlicffi (==1.0.9.2)
Requires-Dist: ConfigParser (==5.3.0)
Requires-Dist: cryptography (==40.0.1)
Requires-Dist: Cython (==0.29.34)
Requires-Dist: dl (==0.1.0)
Requires-Dist: docutils (==0.19)
Requires-Dist: HTMLParser (==0.0.2)
Requires-Dist: importlib-metadata (==6.2.0)
Requires-Dist: keyring (==23.13.1)
Requires-Dist: lockfile (==0.12.2)
Requires-Dist: lxml (==4.9.2)
Requires-Dist: mock (==5.0.1)
Requires-Dist: numpy (==1.24.2)
Requires-Dist: ordereddict (==1.1)
Requires-Dist: podcastparser (==0.6.9)
Requires-Dist: protobuf (==4.22.1)
Requires-Dist: pyOpenSSL (==23.1.1)
Requires-Dist: simplejson (==3.19.1)
Requires-Dist: toml (==0.10.2)
Requires-Dist: tornado (==6.2)
Requires-Dist: tqdm (==4.65.0)
Requires-Dist: urllib3-secure-extra (==0.1.0)
Requires-Dist: zipp (==3.15.0)
Requires-Dist: requests
